gayadsdb/__init__.py
gayadsdb6969-1.3.0.dist-info/METADATA
gayadsdb6969-1.3.0.dist-info/WHEEL
gayadsdb6969-1.3.0.dist-info/top_level.txt
gayadsdb6969-1.3.0.dist-info/RECORD
