Metadata-Version: 2.1
Name: gayadsdb6969
Version: 1.3.0
Summary: sql db made simply easy with essential features needed for db users
Author: Pablo62060
Author-email: iesmks69@gmail.com
